strmscience/__init__.py
strmscience/finance/__init__.py
strmscience/strmscience.py
strmscience-0.1.2.dist-info/WHEEL
strmscience-0.1.2.dist-info/METADATA
strmscience-0.1.2.dist-info/RECORD
