Metadata-Version: 2.1
Name: strmscience
Version: 0.1.2
Summary: STRM base python package
License: GPL-3.0-or-later
Author: OPSXCQ
Author-email: opsxcq@strm.sh
Requires-Python: >=3.7,<4.0
Classifier: License :: OSI Approved :: GNU General Public License v3 or later (GPLv3+)
Classifier: Programming Language :: Python :: 3
Classifier: Programming Language :: Python :: 3.7
Classifier: Programming Language :: Python :: 3.8
Requires-Dist: fbprophet (>=0.6,<0.7)
Requires-Dist: pandas (>=1.1.0,<2.0.0)
Requires-Dist: pulp (>=2.3,<3.0)
Requires-Dist: seaborn (>=0.10.1,<0.11.0)
